Workbook

Sheet Dashboard
A1: Sales & Profit Dashboard
A2: Project: PR. 2 Analyzer
A4: Total Sales | C4: Total Profit | E4: Orders | G4: Avg Order Value | I4: Avg Discount | K4: Profit Margin
A5: =SUM(Dataset!E2:E201) -> 195217.76 | C5: =SUM(Dataset!I2:I201) -> 68287.01 | E5: =COUNTA(Dataset!A2:A201) -> 200 | G5: =AVERAGE(Dataset!E2:E201) -> 976.0888 | I5: =AVERAGE(Dataset!G2:G201) -> 0.09725 | K5: =SUM(Dataset!I2:I201)/SUM(Dataset!E2:E201) -> 0.34979917
A8: Top 10 Customers | I8: Product Sales | K8: Product | L8: Sales
A9: Rank | B9: Customer | C9: Purchase | D9: Profit | K9: Books | L9: =SUMIF(Dataset!$D$2:$D$201,K9,Dataset!$E$2:$E$201) -> 47002.46
A10: 1 | B10: ='High Value Customers'!C39 -> 0 | C10: ='High Value Customers'!D39 -> 0 | D10: ='High Value Customers'!E39 -> 0 | K10: Clothing | L10: =SUMIF(Dataset!$D$2:$D$201,K10,Dataset!$E$2:$E$201) -> 41927.59
A11: 2 | B11: ='High Value Customers'!C40 -> Linda Taylor | C11: ='High Value Customers'!D40 -> 10293.87 | D11: ='High Value Customers'!E40 -> 3541.02 | K11: Electronics | L11: =SUMIF(Dataset!$D$2:$D$201,K11,Dataset!$E$2:$E$201) -> 41044
A12: 3 | B12: ='High Value Customers'!C41 -> Michael Anderson | C12: ='High Value Customers'!D41 -> 9941.88 | D12: ='High Value Customers'!E41 -> 3936.26 | K12: Furniture | L12: =SUMIF(Dataset!$D$2:$D$201,K12,Dataset!$E$2:$E$201) -> 36612.89
A13: 4 | B13: ='High Value Customers'!C42 -> Robert Anderson | C13: ='High Value Customers'!D42 -> 9760.8 | D13: ='High Value Customers'!E42 -> 3442.48 | K13: Office Supplies | L13: =SUMIF(Dataset!$D$2:$D$201,K13,Dataset!$E$2:$E$201) -> 28630.82
A14: 5 | B14: ='High Value Customers'!C43 -> Mary Davis | C14: ='High Value Customers'!D43 -> 9371.81 | D14: ='High Value Customers'!E43 -> 2922.02
A15: 6 | B15: ='High Value Customers'!C44 -> Sarah Anderson | C15: ='High Value Customers'!D44 -> 8740.18 | D15: ='High Value Customers'!E44 -> 2848.62
A16: 7 | B16: ='High Value Customers'!C45 -> Emma Davis | C16: ='High Value Customers'!D45 -> 8490.18 | D16: ='High Value Customers'!E45 -> 2652.75
A17: 8 | B17: ='High Value Customers'!C46 -> Robert Anderson | C17: ='High Value Customers'!D46 -> 8339 | D17: ='High Value Customers'!E46 -> 2988.71
A18: 9 | B18: ='High Value Customers'!C47 -> James Wilson | C18: ='High Value Customers'!D47 -> 7928.71 | D18: ='High Value Customers'!E47 -> 2965.48
A19: 10 | B19: ='High Value Customers'!C48 -> Lisa Thomas | C19: ='High Value Customers'!D48 -> 7813.59 | D19: ='High Value Customers'!E48 -> 3211.82
A29: Key Insights | J29: Data Quality
A30: Key Findings | J30: ⚠ Repeated Customer_IDs have inconsistent Customer_Name values.
A31: • Overall profit margin: 35.0%.
A32: • Top region by sales: West. Top product category: Books.
A33: • Best sales month: 2024-09 at ₹20,533.50.
A34: • Customer rankings use Customer_ID because names are inconsistent for repeated IDs.
A35: Key Findings
A36: - Sales and profit increase together in the data.
A37: - West has the highest sales among the regions.
A38: - Books is the highest-selling product category.
A39: - Some Customer_IDs have more than one customer name in the source data.
A40: - The discount table shows how profit changes if sales stay the same.

Sheet Project Instructions
A1: PR. 2 Analyzer
A2: Topics: - Conditional Formatting - WHAT IF Analysis - Linear Regression (Using Data Analysis Toolpak) - Data Analysis Feature (Descriptive Stats, Regression, Histogram) - Data Storytelling - Add Symbols or Arrows in Custom Formatting - Create Timestamp - Find High-Value Customers using Groupby(), index(), and match() combination - Advanced Descriptive Analytics - Pivot Table with Dashboard - Creating bar charts - Creating line charts - Creating pie charts Main Tasks: 1. Apply conditional formatting to highlight top 10 customers based on total purchase. 2. Perform WHAT IF Analysis to see impact of changing discount on total profit. 3. Use Data Analysis Toolpak to run Linear Regression (Profit vs Sales). 4. Use 'Descriptive Statistics' from Analysis Toolpak on the dataset. 5. Add up/down arrows on monthly sales growth. 6. Create a timestamp column using NOW(). 7. Identify high-value customers using index(), match(), and filters. 8. Create Pivot Table to analyze total sales by region and product. 9. Create bar, line, and pie charts to visualize KPIs. 10. Summarize insights using a dashboard. Deliverable: Complete the given worksheet by applying the required formulas in respective sheets.

Sheet Dataset
A1: Customer_ID | B1: Customer_Name | C1: Region | D1: Product_Category | E1: Sales | F1: Quantity | G1: Discount | H1: Order_Date | I1: Profit | J1: Timestamp | K1: Customer_Total_Purchase | L1: Customer_Total_Profit
A2: CUST019 | B2: James Davis | C2: West | D2: Books | E2: 1036.09 | F2: 4 | G2: 0.2 | H2: 45392 | I2: 331.55 | J2: =NOW() -> 46303.433 | K2: =SUMIF($A$2:$A$201,A2,$E$2:$E$201) -> 4640.11 | L2: =SUMIF($A$2:$A$201,A2,$I$2:$I$201) -> 1721.12
A3: CUST012 | B3: Robert Anderson | C3: West | D3: Clothing | E3: 1101.28 | F3: 3 | G3: 0.2 | H3: 45393 | I3: 440.51 | J3: =NOW() -> 46303.433 | K3: =SUMIF($A$2:$A$201,A3,$E$2:$E$201) -> 8339 | L3: =SUMIF($A$2:$A$201,A3,$I$2:$I$201) -> 2988.71
A4: CUST017 | B4: James Taylor | C4: East | D4: Books | E4: 713.34 | F4: 17 | G4: 0 | H4: 45396 | I4: 285.34 | J4: =NOW() -> 46303.433 | K4: =SUMIF($A$2:$A$201,A4,$E$2:$E$201) -> 3419.2 | L4: =SUMIF($A$2:$A$201,A4,$I$2:$I$201) -> 1257.21
A5: CUST005 | B5: Robert Anderson | C5: South | D5: Electronics | E5: 760.93 | F5: 4 | G5: 0.15 | H5: 45396 | I5: 161.7 | J5: =NOW() -> 46303.433 | K5: =SUMIF($A$2:$A$201,A5,$E$2:$E$201) -> 6666.13 | L5: =SUMIF($A$2:$A$201,A5,$I$2:$I$201) -> 1982.39
A6: CUST030 | B6: James Wilson | C6: North | D6: Books | E6: 847 | F6: 12 | G6: 0.2 | H6: 45397 | I6: 271.04 | J6: =NOW() -> 46303.433 | K6: =SUMIF($A$2:$A$201,A6,$E$2:$E$201) -> 7928.71 | L6: =SUMIF($A$2:$A$201,A6,$I$2:$I$201) -> 2965.48
A7: CUST007 | B7: Michael Anderson | C7: North | D7: Furniture | E7: 965.64 | F7: 8 | G7: 0.1 | H7: 45398 | I7: 304.18 | J7: =NOW() -> 46303.433 | K7: =SUMIF($A$2:$A$201,A7,$E$2:$E$201) -> 9941.88 | L7: =SUMIF($A$2:$A$201,A7,$I$2:$I$201) -> 3936.26
A8: CUST001 | B8: Linda Wilson | C8: West | D8: Electronics | E8: 1317.53 | F8: 12 | G8: 0.05 | H8: 45398 | I8: 312.91 | J8: =NOW() -> 46303.433 | K8: =SUMIF($A$2:$A$201,A8,$E$2:$E$201) -> 6549.55 | L8: =SUMIF($A$2:$A$201,A8,$I$2:$I$201) -> 1868.77
A9: CUST026 | B9: Mary Davis | C9: East | D9: Furniture | E9: 1074.47 | F9: 6 | G9: 0.2 | H9: 45401 | I9: 300.85 | J9: =NOW() -> 46303.433 | K9: =SUMIF($A$2:$A$201,A9,$E$2:$E$201) -> 9371.81 | L9: =SUMIF($A$2:$A$201,A9,$I$2:$I$201) -> 2922.02
A10: CUST009 | B10: Linda Jackson | C10: Central | D10: Books | E10: 501.54 | F10: 11 | G10: 0.05 | H10: 45401 | I10: 190.59 | J10: =NOW() -> 46303.433 | K10: =SUMIF($A$2:$A$201,A10,$E$2:$E$201) -> 6505.2 | L10: =SUMIF($A$2:$A$201,A10,$I$2:$I$201) -> 2052.54
A11: CUST010 | B11: David Thomas | C11: Central | D11: Clothing | E11: 737.31 | F11: 2 | G11: 0.05 | H11: 45401 | I11: 350.22 | J11: =NOW() -> 46303.433 | K11: =SUMIF($A$2:$A$201,A11,$E$2:$E$201) -> 4259.22 | L11: =SUMIF($A$2:$A$201,A11,$I$2:$I$201) -> 1529.32
A12: CUST014 | B12: Emma Davis | C12: West | D12: Office Supplies | E12: 1572.82 | F12: 6 | G12: 0.05 | H12: 45402 | I12: 672.38 | J12: =NOW() -> 46303.433 | K12: =SUMIF($A$2:$A$201,A12,$E$2:$E$201) -> 6729.89 | L12: =SUMIF($A$2:$A$201,A12,$I$2:$I$201) -> 2507.18
A13: CUST014 | B13: David Thomas | C13: Central | D13: Books | E13: 1343.13 | F13: 14 | G13: 0.15 | H13: 45404 | I13: 456.66 | J13: =NOW() -> 46303.433 | K13: =SUMIF($A$2:$A$201,A13,$E$2:$E$201) -> 6729.89 | L13: =SUMIF($A$2:$A$201,A13,$I$2:$I$201) -> 2507.18
... A201: CUST016 | B201: David Thomas | C201: South | D201: Clothing | E201: 928.32 | F201: 2 | G201: 0.05 | H201: 45754 | I201: 440.95 | J201: =NOW() -> 46303.433 | K201: =SUMIF($A$2:$A$201,A201,$E$2:$E$201) -> 3369.17 | L201: =SUMIF($A$2:$A$201,A201,$I$2:$I$201) -> 1497.25

Sheet Analysis
A1: Monthly Sales Analysis
A3: Monthly Sales
A4: Month | B4: Sales | C4: Profit | D4: Orders | E4: Sales Growth | F4: Growth Indicator
A5: 45383 | B5: =SUMIFS(Dataset!$E$2:$E$201,Dataset!$H$2:$H$201,">="&A5,Dataset!$H$2:$H$201,"<"&EDATE(A5,1)) -> 19029.96 | C5: =SUMIFS(Dataset!$I$2:$I$201,Dataset!$H$2:$H$201,">="&A5,Dataset!$H$2:$H$201,"<"&EDATE(A5,1)) -> 6244.01 | D5: =COUNTIFS(Dataset!$H$2:$H$201,">="&A5,Dataset!$H$2:$H$201,"<"&EDATE(A5,1)) -> 19 | E5: N/A | F5: —
A6: 45413 | B6: =SUMIFS(Dataset!$E$2:$E$201,Dataset!$H$2:$H$201,">="&A6,Dataset!$H$2:$H$201,"<"&EDATE(A6,1)) -> 18507.34 | C6: =SUMIFS(Dataset!$I$2:$I$201,Dataset!$H$2:$H$201,">="&A6,Dataset!$H$2:$H$201,"<"&EDATE(A6,1)) -> 6121.35 | D6: =COUNTIFS(Dataset!$H$2:$H$201,">="&A6,Dataset!$H$2:$H$201,"<"&EDATE(A6,1)) -> 21 | E6: =IFERROR(B6/B5-1,0) -> -0.027463011 | F6: =IF(E6>0,"▲",IF(E6<0,"▼","—")) -> ▼
A7: 45444 | B7: =SUMIFS(Dataset!$E$2:$E$201,Dataset!$H$2:$H$201,">="&A7,Dataset!$H$2:$H$201,"<"&EDATE(A7,1)) -> 20187.51 | C7: =SUMIFS(Dataset!$I$2:$I$201,Dataset!$H$2:$H$201,">="&A7,Dataset!$H$2:$H$201,"<"&EDATE(A7,1)) -> 6918 | D7: =COUNTIFS(Dataset!$H$2:$H$201,">="&A7,Dataset!$H$2:$H$201,"<"&EDATE(A7,1)) -> 20 | E7: =IFERROR(B7/B6-1,0) -> 0.090783981 | F7: =IF(E7>0,"▲",IF(E7<0,"▼","—")) -> ▲
A8: 45474 | B8: =SUMIFS(Dataset!$E$2:$E$201,Dataset!$H$2:$H$201,">="&A8,Dataset!$H$2:$H$201,"<"&EDATE(A8,1)) -> 11609.04 | C8: =SUMIFS(Dataset!$I$2:$I$201,Dataset!$H$2:$H$201,">="&A8,Dataset!$H$2:$H$201,"<"&EDATE(A8,1)) -> 3743.85 | D8: =COUNTIFS(Dataset!$H$2:$H$201,">="&A8,Dataset!$H$2:$H$201,"<"&EDATE(A8,1)) -> 12 | E8: =IFERROR(B8/B7-1,0) -> -0.42493948 | F8: =IF(E8>0,"▲",IF(E8<0,"▼","—")) -> ▼
A9: 45505 | B9: =SUMIFS(Dataset!$E$2:$E$201,Dataset!$H$2:$H$201,">="&A9,Dataset!$H$2:$H$201,"<"&EDATE(A9,1)) -> 10091.7 | C9: =SUMIFS(Dataset!$I$2:$I$201,Dataset!$H$2:$H$201,">="&A9,Dataset!$H$2:$H$201,"<"&EDATE(A9,1)) -> 3302.84 | D9: =COUNTIFS(Dataset!$H$2:$H$201,">="&A9,Dataset!$H$2:$H$201,"<"&EDATE(A9,1)) -> 10 | E9: =IFERROR(B9/B8-1,0) -> -0.13070331 | F9: =IF(E9>0,"▲",IF(E9<0,"▼","—")) -> ▼
A10: 45536 | B10: =SUMIFS(Dataset!$E$2:$E$201,Dataset!$H$2:$H$201,">="&A10,Dataset!$H$2:$H$201,"<"&EDATE(A10,1)) -> 20533.5 | C10: =SUMIFS(Dataset!$I$2:$I$201,Dataset!$H$2:$H$201,">="&A10,Dataset!$H$2:$H$201,"<"&EDATE(A10,1)) -> 7457.52 | D10: =COUNTIFS(Dataset!$H$2:$H$201,">="&A10,Dataset!$H$2:$H$201,"<"&EDATE(A10,1)) -> 20 | E10: =IFERROR(B10/B9-1,0) -> 1.0346919 | F10: =IF(E10>0,"▲",IF(E10<0,"▼","—")) -> ▲
A11: 45566 | B11: =SUMIFS(Dataset!$E$2:$E$201,Dataset!$H$2:$H$201,">="&A11,Dataset!$H$2:$H$201,"<"&EDATE(A11,1)) -> 14215.24 | C11: =SUMIFS(Dataset!$I$2:$I$201,Dataset!$H$2:$H$201,">="&A11,Dataset!$H$2:$H$201,"<"&EDATE(A11,1)) -> 4861.7 | D11: =COUNTIFS(Dataset!$H$2:$H$201,">="&A11,Dataset!$H$2:$H$201,"<"&EDATE(A11,1)) -> 14 | E11: =IFERROR(B11/B10-1,0) -> -0.30770497 | F11: =IF(E11>0,"▲",IF(E11<0,"▼","—")) -> ▼
A12: 45597 | B12: =SUMIFS(Dataset!$E$2:$E$201,Dataset!$H$2:$H$201,">="&A12,Dataset!$H$2:$H$201,"<"&EDATE(A12,1)) -> 20135.03 | C12: =SUMIFS(Dataset!$I$2:$I$201,Dataset!$H$2:$H$201,">="&A12,Dataset!$H$2:$H$201,"<"&EDATE(A12,1)) -> 6814.88 | D12: =COUNTIFS(Dataset!$H$2:$H$201,">="&A12,Dataset!$H$2:$H$201,"<"&EDATE(A12,1)) -> 20 | E12: =IFERROR(B12/B11-1,0) -> 0.41643968 | F12: =IF(E12>0,"▲",IF(E12<0,"▼","—")) -> ▲
A13: 45627 | B13: =SUMIFS(Dataset!$E$2:$E$201,Dataset!$H$2:$H$201,">="&A13,Dataset!$H$2:$H$201,"<"&EDATE(A13,1)) -> 11120.04 | C13: =SUMIFS(Dataset!$I$2:$I$201,Dataset!$H$2:$H$201,">="&A13,Dataset!$H$2:$H$201,"<"&EDATE(A13,1)) -> 3549.99 | D13: =COUNTIFS(Dataset!$H$2:$H$201,">="&A13,Dataset!$H$2:$H$201,"<"&EDATE(A13,1)) -> 11 | E13: =IFERROR(B13/B12-1,0) -> -0.44772667 | F13: =IF(E13>0,"▲",IF(E13<0,"▼","—")) -> ▼
A14: 45658 | B14: =SUMIFS(Dataset!$E$2:$E$201,Dataset!$H$2:$H$201,">="&A14,Dataset!$H$2:$H$201,"<"&EDATE(A14,1)) -> 14914.65 | C14: =SUMIFS(Dataset!$I$2:$I$201,Dataset!$H$2:$H$201,">="&A14,Dataset!$H$2:$H$201,"<"&EDATE(A14,1)) -> 5763.4 | D14: =COUNTIFS(Dataset!$H$2:$H$201,">="&A14,Dataset!$H$2:$H$201,"<"&EDATE(A14,1)) -> 16 | E14: =IFERROR(B14/B13-1,0) -> 0.34124068 | F14: =IF(E14>0,"▲",IF(E14<0,"▼","—")) -> ▲
A15: 45689 | B15: =SUMIFS(Dataset!$E$2:$E$201,Dataset!$H$2:$H$201,">="&A15,Dataset!$H$2:$H$201,"<"&EDATE(A15,1)) -> 14006.36 | C15: =SUMIFS(Dataset!$I$2:$I$201,Dataset!$H$2:$H$201,">="&A15,Dataset!$H$2:$H$201,"<"&EDATE(A15,1)) -> 5039.23 | D15: =COUNTIFS(Dataset!$H$2:$H$201,">="&A15,Dataset!$H$2:$H$201,"<"&EDATE(A15,1)) -> 14 | E15: =IFERROR(B15/B14-1,0) -> -0.060899183 | F15: =IF(E15>0,"▲",IF(E15<0,"▼","—")) -> ▼
A16: 45717 | B16: =SUMIFS(Dataset!$E$2:$E$201,Dataset!$H$2:$H$201,">="&A16,Dataset!$H$2:$H$201,"<"&EDATE(A16,1)) -> 17655.22 | C16: =SUMIFS(Dataset!$I$2:$I$201,Dataset!$H$2:$H$201,">="&A16,Dataset!$H$2:$H$201,"<"&EDATE(A16,1)) -> 7071.39 | D16: =COUNTIFS(Dataset!$H$2:$H$201,">="&A16,Dataset!$H$2:$H$201,"<"&EDATE(A16,1)) -> 19 | E16: =IFERROR(B16/B15-1,0) -> 0.26051451 | F16: =IF(E16>0,"▲",IF(E16<0,"▼","—")) -> ▲
A17: 45748 | B17: =SUMIFS(Dataset!$E$2:$E$201,Dataset!$H$2:$H$201,">="&A17,Dataset!$H$2:$H$201,"<"&EDATE(A17,1)) -> 3212.17 | C17: =SUMIFS(Dataset!$I$2:$I$201,Dataset!$H$2:$H$201,">="&A17,Dataset!$H$2:$H$201,"<"&EDATE(A17,1)) -> 1398.85 | D17: =COUNTIFS(Dataset!$H$2:$H$201,">="&A17,Dataset!$H$2:$H$201,"<"&EDATE(A17,1)) -> 4 | E17: =IFERROR(B17/B16-1,0) -> -0.81806117 | F17: =IF(E17>0,"▲",IF(E17<0,"▼","—")) -> ▼
A20: Sales by Region and Product
A21: Region | B21: Books | C21: Clothing | D21: Electronics | E21: Furniture | F21: Office Supplies | G21: Total
A22: Central | B22: =SUMIFS(Dataset!$E$2:$E$201,Dataset!$C$2:$C$201,$A22,Dataset!$D$2:$D$201,B$21) -> 11297.15 | C22: =SUMIFS(Dataset!$E$2:$E$201,Dataset!$C$2:$C$201,$A22,Dataset!$D$2:$D$201,C$21) -> 12200.26 | D22: =SUMIFS(Dataset!$E$2:$E$201,Dataset!$C$2:$C$201,$A22,Dataset!$D$2:$D$201,D$21) -> 6621.24 | E22: =SUMIFS(Dataset!$E$2:$E$201,Dataset!$C$2:$C$201,$A22,Dataset!$D$2:$D$201,E$21) -> 4876.96 | F22: =SUMIFS(Dataset!$E$2:$E$201,Dataset!$C$2:$C$201,$A22,Dataset!$D$2:$D$201,F$21) -> 8472.72 | G22: =SUM(B22:F22) -> 43468.33
A23: East | B23: =SUMIFS(Dataset!$E$2:$E$201,Dataset!$C$2:$C$201,$A23,Dataset!$D$2:$D$201,B$21) -> 11389.09 | C23: =SUMIFS(Dataset!$E$2:$E$201,Dataset!$C$2:$C$201,$A23,Dataset!$D$2:$D$201,C$21) -> 2401.45 | D23: =SUMIFS(Dataset!$E$2:$E$201,Dataset!$C$2:$C$201,$A23,Dataset!$D$2:$D$201,D$21) -> 2869.54 | E23: =SUMIFS(Dataset!$E$2:$E$201,Dataset!$C$2:$C$201,$A23,Dataset!$D$2:$D$201,E$21) -> 7592.34 | F23: =SUMIFS(Dataset!$E$2:$E$201,Dataset!$C$2:$C$201,$A23,Dataset!$D$2:$D$201,F$21) -> 8189.22 | G23: =SUM(B23:F23) -> 32441.64
A24: North | B24: =SUMIFS(Dataset!$E$2:$E$201,Dataset!$C$2:$C$201,$A24,Dataset!$D$2:$D$201,B$21) -> 8037.01 | C24: =SUMIFS(Dataset!$E$2:$E$201,Dataset!$C$2:$C$201,$A24,Dataset!$D$2:$D$201,C$21) -> 8422.82 | D24: =SUMIFS(Dataset!$E$2:$E$201,Dataset!$C$2:$C$201,$A24,Dataset!$D$2:$D$201,D$21) -> 8191.71 | E24: =SUMIFS(Dataset!$E$2:$E$201,Dataset!$C$2:$C$201,$A24,Dataset!$D$2:$D$201,E$21) -> 6978.08 | F24: =SUMIFS(Dataset!$E$2:$E$201,Dataset!$C$2:$C$201,$A24,Dataset!$D$2:$D$201,F$21) -> 3345.8 | G24: =SUM(B24:F24) -> 34975.42
A25: South | B25: =SUMIFS(Dataset!$E$2:$E$201,Dataset!$C$2:$C$201,$A25,Dataset!$D$2:$D$201,B$21) -> 9588.04 | C25: =SUMIFS(Dataset!$E$2:$E$201,Dataset!$C$2:$C$201,$A25,Dataset!$D$2:$D$201,C$21) -> 8393.63 | D25: =SUMIFS(Dataset!$E$2:$E$201,Dataset!$C$2:$C$201,$A25,Dataset!$D$2:$D$201,D$21) -> 11989.07 | E25: =SUMIFS(Dataset!$E$2:$E$201,Dataset!$C$2:$C$201,$A25,Dataset!$D$2:$D$201,E$21) -> 7982.73 | F25: =SUMIFS(Dataset!$E$2:$E$201,Dataset!$C$2:$C$201,$A25,Dataset!$D$2:$D$201,F$21) -> 2295.32 | G25: =SUM(B25:F25) -> 40248.79
A26: West | B26: =SUMIFS(Dataset!$E$2:$E$201,Dataset!$C$2:$C$201,$A26,Dataset!$D$2:$D$201,B$21) -> 6691.17 | C26: =SUMIFS(Dataset!$E$2:$E$201,Dataset!$C$2:$C$201,$A26,Dataset!$D$2:$D$201,C$21) -> 10509.43 | D26: =SUMIFS(Dataset!$E$2:$E$201,Dataset!$C$2:$C$201,$A26,Dataset!$D$2:$D$201,D$21) -> 11372.44 | E26: =SUMIFS(Dataset!$E$2:$E$201,Dataset!$C$2:$C$201,$A26,Dataset!$D$2:$D$201,E$21) -> 9182.78 | F26: =SUMIFS(Dataset!$E$2:$E$201,Dataset!$C$2:$C$201,$A26,Dataset!$D$2:$D$201,F$21) -> 6327.76 | G26: =SUM(B26:F26) -> 44083.58
A27: Total | B27: =SUM(B22:B26) -> 47002.46 | C27: =SUM(C22:C26) -> 41927.59 | D27: =SUM(D22:D26) -> 41044 | E27: =SUM(E22:E26) -> 36612.89 | F27: =SUM(F22:F26) -> 28630.82 | G27: =SUM(G22:G26) -> 195217.76
A30: Key Findings
A31: • Sales are spread across 13 months, with month-to-month growth varying across the period.
A32: • Sales and profit have a strong positive relationship; higher sales generally correspond to higher profit.
A33: • Customer-level totals reveal a small group of high-value customers who contribute disproportionately to revenue.
A34: • Discount scenarios show that lowering discounts can increase modeled profit when sales volume is held constant.
A35: • Region and product summaries highlight where sales concentration is strongest and support targeted business decisions.

Sheet What If Analysis
A1: WHAT IF Analysis - Discount Impact
A3: Discount Scenarios
A4: Current total profit | B4: =SUM(Dataset!I2:I201) -> 68287.01
A5: Current total sales | B5: =SUM(Dataset!E2:E201) -> 195217.76
A6: Current average discount | B6: =AVERAGE(Dataset!G2:G201) -> 0.09725
A8: Discount Sensitivity Table
A9: Scenario Discount | B9: Discount Change | C9: Modeled Total Profit | D9: Profit Change | E9: Profit Change % | F9: Interpretation
A10: 0 | B10: =A10-$B$6 -> -0.09725 | C10: =$B$4+$B$5*($B$6-A10) -> 87271.937 | D10: =C10-$B$4 -> 18984.927 | E10: =D10/$B$4 -> 0.27801667 | F10: =IF(D10>0,"Higher modeled profit",IF(D10<0,"Lower modeled profit","Baseline")) -> Higher modeled profit
A11: 0.05 | B11: =A11-$B$6 -> -0.04725 | C11: =$B$4+$B$5*($B$6-A11) -> 77511.049 | D11: =C11-$B$4 -> 9224.0392 | E11: =D11/$B$4 -> 0.13507751 | F11: =IF(D11>0,"Higher modeled profit",IF(D11<0,"Lower modeled profit","Baseline")) -> Higher modeled profit
A12: 0.1 | B12: =A12-$B$6 -> 0.00275 | C12: =$B$4+$B$5*($B$6-A12) -> 67750.161 | D12: =C12-$B$4 -> -536.84884 | E12: =D12/$B$4 -> -0.0078616539 | F12: =IF(D12>0,"Higher modeled profit",IF(D12<0,"Lower modeled profit","Baseline")) -> Lower modeled profit
A13: 0.15 | B13: =A13-$B$6 -> 0.05275 | C13: =$B$4+$B$5*($B$6-A13) -> 57989.273 | D13: =C13-$B$4 -> -10297.737 | E13: =D13/$B$4 -> -0.15080082 | F13: =IF(D13>0,"Higher modeled profit",IF(D13<0,"Lower modeled profit","Baseline")) -> Lower modeled profit
A14: 0.2 | B14: =A14-$B$6 -> 0.10275 | C14: =$B$4+$B$5*($B$6-A14) -> 48228.385 | D14: =C14-$B$4 -> -20058.625 | E14: =D14/$B$4 -> -0.29373998 | F14: =IF(D14>0,"Higher modeled profit",IF(D14<0,"Lower modeled profit","Baseline")) -> Lower modeled profit
A15: 0.25 | B15: =A15-$B$6 -> 0.15275 | C15: =$B$4+$B$5*($B$6-A15) -> 38467.497 | D15: =C15-$B$4 -> -29819.513 | E15: =D15/$B$4 -> -0.43667914 | F15: =IF(D15>0,"Higher modeled profit",IF(D15<0,"Lower modeled profit","Baseline")) -> Lower modeled profit
A18: Note: | B18: Modeled profit assumes sales volume stays constant and only the discount changes; this is a sensitivity estimate, not a forecast.
A21: Notes
A22: Lowest discount tested | B22: =MIN(A10:A15) -> 0
A23: Highest modeled profit | B23: =MAX(C10:C15) -> 87271.937
A24: Profit improvement vs current | B24: =B23-$B$4 -> 18984.927

Sheet Regression
A1: Linear Regression - Profit vs Sales
A3: Regression Summary
A4: Multiple R | B4: =CORREL(Dataset!E2:E201,Dataset!I2:I201) -> 0.77340306
A5: R Square | B5: =RSQ(Dataset!I2:I201,Dataset!E2:E201) -> 0.5981523
A6: Adjusted R Square | B6: =1-(1-B5)*(COUNT(Dataset!I2:I201)-1)/(COUNT(Dataset!I2:I201)-2) -> 0.59612277
A7: Standard Error | B7: =STEYX(Dataset!I2:I201,Dataset!E2:E201) -> 86.281231
A8: Observations | B8: =COUNT(Dataset!E2:E201) -> 200
A10: ANOVA
B11: df | C11: SS | D11: MS | E11: F | F11: Significance F
A12: Regression | B12: =1 -> 1 | C12: =RSQ(Dataset!I2:I201,Dataset!E2:E201)*DEVSQ(Dataset!I2:I201) -> 2194058.2 | D12: =C12/B12 -> 2194058.2 | E12: =D12/((DEVSQ(Dataset!I2:I201)-C12)/198) -> 294.72398 | F12: =f.dist.rt(E12,1,198) -> #NAME?
A13: Residual | B13: =198 -> 198 | C13: =DEVSQ(Dataset!I2:I201)-C12 -> 1474001.2 | D13: =C13/B13 -> 7444.4507
A14: Total | B14: =199 -> 199 | C14: =DEVSQ(Dataset!I2:I201) -> 3668059.4
A16: Coefficients
A17: Term | B17: Coefficient | C17: Standard Error | D17: t Stat
A18: Intercept | B18: =INTERCEPT(Dataset!I2:I201,Dataset!E2:E201) -> -1.0315505 | C18: =STEYX(Dataset!I2:I201,Dataset!E2:E201)*SQRT(1/COUNT(Dataset!E2:E201)+(AVERAGE(Dataset!E2:E201)^2)/DEVSQ(Dataset!E2:E201)) -> 20.860617 | D18: =B18/C18 -> -0.049449663
A19: Sales | B19: =SLOPE(Dataset!I2:I201,Dataset!E2:E201) -> 0.35085599 | C19: =STEYX(Dataset!I2:I201,Dataset!E2:E201)/SQRT(DEVSQ(Dataset!E2:E201)) -> 0.020437189 | D19: =B19/C19 -> 17.167527
A21: Equation | B21: ="Profit = "&TEXT(B18,"0.000")&" + "&TEXT(B19,"0.000")&" × Sales" -> Profit = -1.032 + 0.351 × Sales
A22: R Square | B22: =RSQ(Dataset!I2:I201,Dataset!E2:E201) -> 0.5981523
A23: Interpretation | B23: ="Sales explains "&TEXT(B22,"0.0%")&" of the variation in Profit." -> Sales explains 59.8% of the variation in Profit.

Sheet Descriptive Stats
A1: Descriptive Statistics and Histogram
A3: Descriptive Statistics
A4: Statistic | B4: Sales | C4: Profit | D4: Quantity | E4: Discount
A5: Mean | B5: =AVERAGE(Dataset!E2:E201) -> 976.0888 | C5: =AVERAGE(Dataset!I2:I201) -> 341.43505 | D5: =AVERAGE(Dataset!F2:F201) -> 9.995 | E5: =AVERAGE(Dataset!G2:G201) -> 0.09725
A6: Standard Error | B6: =stdev.s(Dataset!E2:E201)/SQRT(COUNT(Dataset!E2:E201)) -> #NAME? | C6: =stdev.s(Dataset!I2:I201)/SQRT(COUNT(Dataset!I2:I201)) -> #NAME? | D6: =stdev.s(Dataset!F2:F201)/SQRT(COUNT(Dataset!F2:F201)) -> #NAME? | E6: =stdev.s(Dataset!G2:G201)/SQRT(COUNT(Dataset!G2:G201)) -> #NAME?
A7: Median | B7: =MEDIAN(Dataset!E2:E201) -> 976.72 | C7: =MEDIAN(Dataset!I2:I201) -> 332.255 | D7: =MEDIAN(Dataset!F2:F201) -> 10 | E7: =MEDIAN(Dataset!G2:G201) -> 0.1
A8: Mode | B8: =mode.sngl(Dataset!E2:E201) -> #NAME? | C8: =mode.sngl(Dataset!I2:I201) -> #NAME? | D8: =mode.sngl(Dataset!F2:F201) -> #NAME? | E8: =mode.sngl(Dataset!G2:G201) -> #NAME?
A9: Standard Deviation | B9: =stdev.s(Dataset!E2:E201) -> #NAME? | C9: =stdev.s(Dataset!I2:I201) -> #NAME? | D9: =stdev.s(Dataset!F2:F201) -> #NAME? | E9: =stdev.s(Dataset!G2:G201) -> #NAME?
A10: Sample Variance | B10: =var.s(Dataset!E2:E201) -> #NAME? | C10: =var.s(Dataset!I2:I201) -> #NAME? | D10: =var.s(Dataset!F2:F201) -> #NAME? | E10: =var.s(Dataset!G2:G201) -> #NAME?
A11: Kurtosis | B11: =KURT(Dataset!E2:E201) -> -0.088595232 | C11: =KURT(Dataset!I2:I201) -> 0.26450644 | D11: =KURT(Dataset!F2:F201) -> -1.2091054 | E11: =KURT(Dataset!G2:G201) -> -1.3257012
A12: Skewness | B12: =SKEW(Dataset!E2:E201) -> 0.14685797 | C12: =SKEW(Dataset!I2:I201) -> 0.57339636 | D12: =SKEW(Dataset!F2:F201) -> 0.060845864 | E12: =SKEW(Dataset!G2:G201) -> 0.096827386
A13: Range | B13: =MAX(Dataset!E2:E201)-MIN(Dataset!E2:E201) -> 1665.15 | C13: =MAX(Dataset!I2:I201)-MIN(Dataset!I2:I201) -> 704.83 | D13: =MAX(Dataset!F2:F201)-MIN(Dataset!F2:F201) -> 18 | E13: =MAX(Dataset!G2:G201)-MIN(Dataset!G2:G201) -> 0.2
A14: Minimum | B14: =MIN(Dataset!E2:E201) -> 258.51 | C14: =MIN(Dataset!I2:I201) -> 64.63 | D14: =MIN(Dataset!F2:F201) -> 1 | E14: =MIN(Dataset!G2:G201) -> 0
A15: Maximum | B15: =MAX(Dataset!E2:E201) -> 1923.66 | C15: =MAX(Dataset!I2:I201) -> 769.46 | D15: =MAX(Dataset!F2:F201) -> 19 | E15: =MAX(Dataset!G2:G201) -> 0.2
A16: Sum | B16: =SUM(Dataset!E2:E201) -> 195217.76 | C16: =SUM(Dataset!I2:I201) -> 68287.01 | D16: =SUM(Dataset!F2:F201) -> 1999 | E16: =SUM(Dataset!G2:G201) -> 19.45
A17: Count | B17: =COUNT(Dataset!E2:E201) -> 200 | C17: =COUNT(Dataset!I2:I201) -> 200 | D17: =COUNT(Dataset!F2:F201) -> 200 | E17: =COUNT(Dataset!G2:G201) -> 200
A19: Sales Histogram Bins
A20: 0–500 | B20: =COUNTIFS(Dataset!$E$2:$E$201,">="&0,Dataset!$E$2:$E$201,"<"&500) -> 11
A21: 250–750 | B21: =COUNTIFS(Dataset!$E$2:$E$201,">="&250,Dataset!$E$2:$E$201,"<"&750) -> 48
A22: 500–1000 | B22: =COUNTIFS(Dataset!$E$2:$E$201,">="&500,Dataset!$E$2:$E$201,"<"&1000) -> 95
A23: 750–1250 | B23: =COUNTIFS(Dataset!$E$2:$E$201,">="&750,Dataset!$E$2:$E$201,"<"&1250) -> 118
A24: 1000–1500 | B24: =COUNTIFS(Dataset!$E$2:$E$201,">="&1000,Dataset!$E$2:$E$201,"<"&1500) -> 85
A25: 1250–1750 | B25: =COUNTIFS(Dataset!$E$2:$E$201,">="&1250,Dataset!$E$2:$E$201,"<"&1750) -> 33
A26: 1500–2000 | B26: =COUNTIFS(Dataset!$E$2:$E$201,">="&1500,Dataset!$E$2:$E$201,"<"&2000) -> 9
A27: 1750+ | B27: =COUNTIF(Dataset!$E$2:$E$201,">="&1750) -> 1
A28: 2000+ | B28: =COUNTIF(Dataset!$E$2:$E$201,">="&2000) -> 0
A29: 1400-1600 | B29: =COUNTIFS(Dataset!$E$2:$E$201,">1400",Dataset!$E$2:$E$201,"<=1600") -> 14
A30: 1600-1800 | B30: =COUNTIFS(Dataset!$E$2:$E$201,">1600",Dataset!$E$2:$E$201,"<=1800") -> 3
A31: 1800-2000 | B31: =COUNTIFS(Dataset!$E$2:$E$201,">1800",Dataset!$E$2:$E$201,"<=2000") -> 1

Sheet High Value Customers
A1: High-Value Customer Analysis
A3: Customer Totals
A4: Customer_ID | B4: Customer_Name (INDEX/MATCH) | C4: Total Purchase | D4: Total Profit | E4: Rank | F4: High Value?
A5: CUST001 | B5: =INDEX(Dataset!$B$2:$B$201,MATCH(A5,Dataset!$A$2:$A$201,0)) -> Linda Wilson | C5: =SUMIF(Dataset!$A$2:$A$201,A5,Dataset!$E$2:$E$201) -> 6549.55 | D5: =SUMIF(Dataset!$A$2:$A$201,A5,Dataset!$I$2:$I$201) -> 1868.77 | E5: =RANK(C5,$C$5:$C$34,0) -> 15 | F5: =IF(E5<=10,"TOP 10","")
A6: CUST002 | B6: =INDEX(Dataset!$B$2:$B$201,MATCH(A6,Dataset!$A$2:$A$201,0)) -> Lisa Davis | C6: =SUMIF(Dataset!$A$2:$A$201,A6,Dataset!$E$2:$E$201) -> 6481.43 | D6: =SUMIF(Dataset!$A$2:$A$201,A6,Dataset!$I$2:$I$201) -> 2210.74 | E6: =RANK(C6,$C$5:$C$34,0) -> 17 | F6: =IF(E6<=10,"TOP 10","")
A7: CUST003 | B7: =INDEX(Dataset!$B$2:$B$201,MATCH(A7,Dataset!$A$2:$A$201,0)) -> Emma Davis | C7: =SUMIF(Dataset!$A$2:$A$201,A7,Dataset!$E$2:$E$201) -> 8490.18 | D7: =SUMIF(Dataset!$A$2:$A$201,A7,Dataset!$I$2:$I$201) -> 2652.75 | E7: =RANK(C7,$C$5:$C$34,0) -> 7 | F7: =IF(E7<=10,"TOP 10","") -> TOP 10
A8: CUST004 | B8: =INDEX(Dataset!$B$2:$B$201,MATCH(A8,Dataset!$A$2:$A$201,0)) -> Lisa Thomas | C8: =SUMIF(Dataset!$A$2:$A$201,A8,Dataset!$E$2:$E$201) -> 7813.59 | D8: =SUMIF(Dataset!$A$2:$A$201,A8,Dataset!$I$2:$I$201) -> 3211.82 | E8: =RANK(C8,$C$5:$C$34,0) -> 10 | F8: =IF(E8<=10,"TOP 10","") -> TOP 10
A9: CUST005 | B9: =INDEX(Dataset!$B$2:$B$201,MATCH(A9,Dataset!$A$2:$A$201,0)) -> Robert Anderson | C9: =SUMIF(Dataset!$A$2:$A$201,A9,Dataset!$E$2:$E$201) -> 6666.13 | D9: =SUMIF(Dataset!$A$2:$A$201,A9,Dataset!$I$2:$I$201) -> 1982.39 | E9: =RANK(C9,$C$5:$C$34,0) -> 14 | F9: =IF(E9<=10,"TOP 10","")
A10: CUST006 | B10: =INDEX(Dataset!$B$2:$B$201,MATCH(A10,Dataset!$A$2:$A$201,0)) -> Mary Jackson | C10: =SUMIF(Dataset!$A$2:$A$201,A10,Dataset!$E$2:$E$201) -> 2699.75 | D10: =SUMIF(Dataset!$A$2:$A$201,A10,Dataset!$I$2:$I$201) -> 837.06 | E10: =RANK(C10,$C$5:$C$34,0) -> 30 | F10: =IF(E10<=10,"TOP 10","")
A11: CUST007 | B11: =INDEX(Dataset!$B$2:$B$201,MATCH(A11,Dataset!$A$2:$A$201,0)) -> Michael Anderson | C11: =SUMIF(Dataset!$A$2:$A$201,A11,Dataset!$E$2:$E$201) -> 9941.88 | D11: =SUMIF(Dataset!$A$2:$A$201,A11,Dataset!$I$2:$I$201) -> 3936.26 | E11: =RANK(C11,$C$5:$C$34,0) -> 3 | F11: =IF(E11<=10,"TOP 10","") -> TOP 10
A12: CUST008 | B12: =INDEX(Dataset!$B$2:$B$201,MATCH(A12,Dataset!$A$2:$A$201,0)) -> Robert Anderson | C12: =SUMIF(Dataset!$A$2:$A$201,A12,Dataset!$E$2:$E$201) -> 9760.8 | D12: =SUMIF(Dataset!$A$2:$A$201,A12,Dataset!$I$2:$I$201) -> 3442.48 | E12: =RANK(C12,$C$5:$C$34,0) -> 4 | F12: =IF(E12<=10,"TOP 10","") -> TOP 10
A13: CUST009 | B13: =INDEX(Dataset!$B$2:$B$201,MATCH(A13,Dataset!$A$2:$A$201,0)) -> Linda Jackson | C13: =SUMIF(Dataset!$A$2:$A$201,A13,Dataset!$E$2:$E$201) -> 6505.2 | D13: =SUMIF(Dataset!$A$2:$A$201,A13,Dataset!$I$2:$I$201) -> 2052.54 | E13: =RANK(C13,$C$5:$C$34,0) -> 16 | F13: =IF(E13<=10,"TOP 10","")
A14: CUST010 | B14: =INDEX(Dataset!$B$2:$B$201,MATCH(A14,Dataset!$A$2:$A$201,0)) -> David Thomas | C14: =SUMIF(Dataset!$A$2:$A$201,A14,Dataset!$E$2:$E$201) -> 4259.22 | D14: =SUMIF(Dataset!$A$2:$A$201,A14,Dataset!$I$2:$I$201) -> 1529.32 | E14: =RANK(C14,$C$5:$C$34,0) -> 24 | F14: =IF(E14<=10,"TOP 10","")
A15: CUST011 | B15: =INDEX(Dataset!$B$2:$B$201,MATCH(A15,Dataset!$A$2:$A$201,0)) -> Mary Davis | C15: =SUMIF(Dataset!$A$2:$A$201,A15,Dataset!$E$2:$E$201) -> 3762.29 | D15: =SUMIF(Dataset!$A$2:$A$201,A15,Dataset!$I$2:$I$201) -> 1545.04 | E15: =RANK(C15,$C$5:$C$34,0) -> 27 | F15: =IF(E15<=10,"TOP 10","")
A16: CUST012 | B16: =INDEX(Dataset!$B$2:$B$201,MATCH(A16,Dataset!$A$2:$A$201,0)) -> Robert Anderson | C16: =SUMIF(Dataset!$A$2:$A$201,A16,Dataset!$E$2:$E$201) -> 8339 | D16: =SUMIF(Dataset!$A$2:$A$201,A16,Dataset!$I$2:$I$201) -> 2988.71 | E16: =RANK(C16,$C$5:$C$34,0) -> 8 | F16: =IF(E16<=10,"TOP 10","") -> TOP 10
... A34: CUST030 | B34: =INDEX(Dataset!$B$2:$B$201,MATCH(A34,Dataset!$A$2:$A$201,0)) -> James Wilson | C34: =SUMIF(Dataset!$A$2:$A$201,A34,Dataset!$E$2:$E$201) -> 7928.71 | D34: =SUMIF(Dataset!$A$2:$A$201,A34,Dataset!$I$2:$I$201) -> 2965.48 | E34: =RANK(C34,$C$5:$C$34,0) -> 9 | F34: =IF(E34<=10,"TOP 10","") -> TOP 10
A37: Top 10 Customers
A38: Note | B38: Customer_ID is used for grouping because some IDs have different names.
A39: 1
A40: 2 | B40: =INDEX($A$5:$A$34,MATCH(A40,$E$5:$E$34,0)) -> CUST028 | C40: =INDEX($B$5:$B$34,MATCH(A40,$E$5:$E$34,0)) -> Linda Taylor | D40: =INDEX($C$5:$C$34,MATCH(A40,$E$5:$E$34,0)) -> 10293.87 | E40: =INDEX($D$5:$D$34,MATCH(A40,$E$5:$E$34,0)) -> 3541.02 | F40: "High Value"
A41: 3 | B41: =INDEX($A$5:$A$34,MATCH(A41,$E$5:$E$34,0)) -> CUST007 | C41: =INDEX($B$5:$B$34,MATCH(A41,$E$5:$E$34,0)) -> Michael Anderson | D41: =INDEX($C$5:$C$34,MATCH(A41,$E$5:$E$34,0)) -> 9941.88 | E41: =INDEX($D$5:$D$34,MATCH(A41,$E$5:$E$34,0)) -> 3936.26 | F41: "High Value"
A42: 4 | B42: =INDEX($A$5:$A$34,MATCH(A42,$E$5:$E$34,0)) -> CUST008 | C42: =INDEX($B$5:$B$34,MATCH(A42,$E$5:$E$34,0)) -> Robert Anderson | D42: =INDEX($C$5:$C$34,MATCH(A42,$E$5:$E$34,0)) -> 9760.8 | E42: =INDEX($D$5:$D$34,MATCH(A42,$E$5:$E$34,0)) -> 3442.48 | F42: "High Value"
A43: 5 | B43: =INDEX($A$5:$A$34,MATCH(A43,$E$5:$E$34,0)) -> CUST026 | C43: =INDEX($B$5:$B$34,MATCH(A43,$E$5:$E$34,0)) -> Mary Davis | D43: =INDEX($C$5:$C$34,MATCH(A43,$E$5:$E$34,0)) -> 9371.81 | E43: =INDEX($D$5:$D$34,MATCH(A43,$E$5:$E$34,0)) -> 2922.02 | F43: "High Value"
A44: 6 | B44: =INDEX($A$5:$A$34,MATCH(A44,$E$5:$E$34,0)) -> CUST021 | C44: =INDEX($B$5:$B$34,MATCH(A44,$E$5:$E$34,0)) -> Sarah Anderson | D44: =INDEX($C$5:$C$34,MATCH(A44,$E$5:$E$34,0)) -> 8740.18 | E44: =INDEX($D$5:$D$34,MATCH(A44,$E$5:$E$34,0)) -> 2848.62 | F44: "High Value"
A45: 7 | B45: =INDEX($A$5:$A$34,MATCH(A45,$E$5:$E$34,0)) -> CUST003 | C45: =INDEX($B$5:$B$34,MATCH(A45,$E$5:$E$34,0)) -> Emma Davis | D45: =INDEX($C$5:$C$34,MATCH(A45,$E$5:$E$34,0)) -> 8490.18 | E45: =INDEX($D$5:$D$34,MATCH(A45,$E$5:$E$34,0)) -> 2652.75 | F45: "High Value"
A46: 8 | B46: =INDEX($A$5:$A$34,MATCH(A46,$E$5:$E$34,0)) -> CUST012 | C46: =INDEX($B$5:$B$34,MATCH(A46,$E$5:$E$34,0)) -> Robert Anderson | D46: =INDEX($C$5:$C$34,MATCH(A46,$E$5:$E$34,0)) -> 8339 | E46: =INDEX($D$5:$D$34,MATCH(A46,$E$5:$E$34,0)) -> 2988.71 | F46: "High Value"
A47: 9 | B47: =INDEX($A$5:$A$34,MATCH(A47,$E$5:$E$34,0)) -> CUST030 | C47: =INDEX($B$5:$B$34,MATCH(A47,$E$5:$E$34,0)) -> James Wilson | D47: =INDEX($C$5:$C$34,MATCH(A47,$E$5:$E$34,0)) -> 7928.71 | E47: =INDEX($D$5:$D$34,MATCH(A47,$E$5:$E$34,0)) -> 2965.48 | F47: "High Value"
A48: 10 | B48: =INDEX($A$5:$A$34,MATCH(A48,$E$5:$E$34,0)) -> CUST004 | C48: =INDEX($B$5:$B$34,MATCH(A48,$E$5:$E$34,0)) -> Lisa Thomas | D48: =INDEX($C$5:$C$34,MATCH(A48,$E$5:$E$34,0)) -> 7813.59 | E48: =INDEX($D$5:$D$34,MATCH(A48,$E$5:$E$34,0)) -> 3211.82 | F48: "High Value"
A51: Sales by Region and Product
A52: Region / Product | B52: Books | C52: Clothing | D52: Electronics | E52: Furniture | F52: Office Supplies | G52: Total
A53: Central | B53: =SUMIFS(Dataset!$E$2:$E$201,Dataset!$C$2:$C$201,$A53,Dataset!$D$2:$D$201,B$52) -> 11297.15 | C53: =SUMIFS(Dataset!$E$2:$E$201,Dataset!$C$2:$C$201,$A53,Dataset!$D$2:$D$201,C$52) -> 12200.26 | D53: =SUMIFS(Dataset!$E$2:$E$201,Dataset!$C$2:$C$201,$A53,Dataset!$D$2:$D$201,D$52) -> 6621.24 | E53: =SUMIFS(Dataset!$E$2:$E$201,Dataset!$C$2:$C$201,$A53,Dataset!$D$2:$D$201,E$52) -> 4876.96 | F53: =SUMIFS(Dataset!$E$2:$E$201,Dataset!$C$2:$C$201,$A53,Dataset!$D$2:$D$201,F$52) -> 8472.72 | G53: =SUM(B53:F53) -> 43468.33
A54: East | B54: =SUMIFS(Dataset!$E$2:$E$201,Dataset!$C$2:$C$201,$A54,Dataset!$D$2:$D$201,B$52) -> 11389.09 | C54: =SUMIFS(Dataset!$E$2:$E$201,Dataset!$C$2:$C$201,$A54,Dataset!$D$2:$D$201,C$52) -> 2401.45 | D54: =SUMIFS(Dataset!$E$2:$E$201,Dataset!$C$2:$C$201,$A54,Dataset!$D$2:$D$201,D$52) -> 2869.54 | E54: =SUMIFS(Dataset!$E$2:$E$201,Dataset!$C$2:$C$201,$A54,Dataset!$D$2:$D$201,E$52) -> 7592.34 | F54: =SUMIFS(Dataset!$E$2:$E$201,Dataset!$C$2:$C$201,$A54,Dataset!$D$2:$D$201,F$52) -> 8189.22 | G54: =SUM(B54:F54) -> 32441.64
A55: North | B55: =SUMIFS(Dataset!$E$2:$E$201,Dataset!$C$2:$C$201,$A55,Dataset!$D$2:$D$201,B$52) -> 8037.01 | C55: =SUMIFS(Dataset!$E$2:$E$201,Dataset!$C$2:$C$201,$A55,Dataset!$D$2:$D$201,C$52) -> 8422.82 | D55: =SUMIFS(Dataset!$E$2:$E$201,Dataset!$C$2:$C$201,$A55,Dataset!$D$2:$D$201,D$52) -> 8191.71 | E55: =SUMIFS(Dataset!$E$2:$E$201,Dataset!$C$2:$C$201,$A55,Dataset!$D$2:$D$201,E$52) -> 6978.08 | F55: =SUMIFS(Dataset!$E$2:$E$201,Dataset!$C$2:$C$201,$A55,Dataset!$D$2:$D$201,F$52) -> 3345.8 | G55: =SUM(B55:F55) -> 34975.42
A56: South | B56: =SUMIFS(Dataset!$E$2:$E$201,Dataset!$C$2:$C$201,$A56,Dataset!$D$2:$D$201,B$52) -> 9588.04 | C56: =SUMIFS(Dataset!$E$2:$E$201,Dataset!$C$2:$C$201,$A56,Dataset!$D$2:$D$201,C$52) -> 8393.63 | D56: =SUMIFS(Dataset!$E$2:$E$201,Dataset!$C$2:$C$201,$A56,Dataset!$D$2:$D$201,D$52) -> 11989.07 | E56: =SUMIFS(Dataset!$E$2:$E$201,Dataset!$C$2:$C$201,$A56,Dataset!$D$2:$D$201,E$52) -> 7982.73 | F56: =SUMIFS(Dataset!$E$2:$E$201,Dataset!$C$2:$C$201,$A56,Dataset!$D$2:$D$201,F$52) -> 2295.32 | G56: =SUM(B56:F56) -> 40248.79
A57: West | B57: =SUMIFS(Dataset!$E$2:$E$201,Dataset!$C$2:$C$201,$A57,Dataset!$D$2:$D$201,B$52) -> 6691.17 | C57: =SUMIFS(Dataset!$E$2:$E$201,Dataset!$C$2:$C$201,$A57,Dataset!$D$2:$D$201,C$52) -> 10509.43 | D57: =SUMIFS(Dataset!$E$2:$E$201,Dataset!$C$2:$C$201,$A57,Dataset!$D$2:$D$201,D$52) -> 11372.44 | E57: =SUMIFS(Dataset!$E$2:$E$201,Dataset!$C$2:$C$201,$A57,Dataset!$D$2:$D$201,E$52) -> 9182.78 | F57: =SUMIFS(Dataset!$E$2:$E$201,Dataset!$C$2:$C$201,$A57,Dataset!$D$2:$D$201,F$52) -> 6327.76 | G57: =SUM(B57:F57) -> 44083.58
A58: Grand Total | B58: =SUM(B53:B57) -> 47002.46 | C58: =SUM(C53:C57) -> 41927.59 | D58: =SUM(D53:D57) -> 41044 | E58: =SUM(E53:E57) -> 36612.89 | F58: =SUM(F53:F57) -> 28630.82 | G58: =SUM(G53:G57) -> 195217.76
